ustd/__init__.py
ustd-0.0.0.dist-info/METADATA
ustd-0.0.0.dist-info/WHEEL
ustd-0.0.0.dist-info/top_level.txt
ustd-0.0.0.dist-info/RECORD
